{
  "algerien-osterreich": {
    "tempC": 26,
    "text": "Gewitter",
    "city": "Kansas City"
  },
  "jordanien-argentinien": {
    "tempC": 29,
    "text": "klar",
    "city": "Dallas"
  },
  "sudafrika-kanada": {
    "tempC": 18,
    "text": "überwiegend klar",
    "city": "Los Angeles"
  },
  "brasilien-japan": {
    "tempC": 28,
    "text": "Gewitter",
    "city": "Houston"
  },
  "deutschland-paraguay": {
    "tempC": 18,
    "text": "klar",
    "city": "Boston"
  },
  "niederlande-marokko": {
    "tempC": 29,
    "text": "klar",
    "city": "Monterrey"
  }
}
