{
  "curacao-elfenbeinkuste": {
    "tempC": 18,
    "text": "teils bewölkt",
    "city": "Philadelphia"
  },
  "ecuador-deutschland": {
    "tempC": 17,
    "text": "klar",
    "city": "New York/New Jersey"
  },
  "tunesien-niederlande": {
    "tempC": 23,
    "text": "bewölkt",
    "city": "Kansas City"
  },
  "japan-schweden": {
    "tempC": 26,
    "text": "klar",
    "city": "Dallas"
  },
  "turkei-usa": {
    "tempC": 17,
    "text": "bewölkt",
    "city": "Los Angeles"
  },
  "paraguay-australien": {
    "tempC": 14,
    "text": "bewölkt",
    "city": "San Francisco"
  },
  "norwegen-frankreich": {
    "tempC": 15,
    "text": "klar",
    "city": "Boston"
  },
  "senegal-irak": {
    "tempC": 11,
    "text": "Nebel",
    "city": "Toronto"
  },
  "kap-verde-saudi-arabien": {
    "tempC": 25,
    "text": "klar",
    "city": "Houston"
  },
  "uruguay-spanien": {
    "tempC": 16,
    "text": "überwiegend klar",
    "city": "Guadalajara"
  },
  "neuseeland-belgien": {
    "tempC": 18,
    "text": "klar",
    "city": "Vancouver"
  },
  "agypten-iran": {
    "tempC": 17,
    "text": "klar",
    "city": "Seattle"
  }
}
