{
  "brasilien-japan": {
    "tempC": 34,
    "text": "Gewitter",
    "city": "Houston"
  },
  "deutschland-paraguay": {
    "tempC": 25,
    "text": "bewölkt",
    "city": "Boston"
  },
  "niederlande-marokko": {
    "tempC": 37,
    "text": "klar",
    "city": "Monterrey"
  },
  "elfenbeinkuste-norwegen": {
    "tempC": 35,
    "text": "Gewitter",
    "city": "Dallas"
  },
  "frankreich-schweden": {
    "tempC": 28,
    "text": "klar",
    "city": "New York/New Jersey"
  },
  "mexiko-ecuador": {
    "tempC": 22,
    "text": "teils bewölkt",
    "city": "Mexiko-Stadt"
  }
}
