{
  "brasilien-norwegen": {
    "tempC": 24,
    "text": "teils bewölkt",
    "city": "New York/New Jersey"
  },
  "mexiko-england": {
    "tempC": 14,
    "text": "bewölkt",
    "city": "Mexiko-Stadt"
  },
  "portugal-spanien": {
    "tempC": 26,
    "text": "überwiegend klar",
    "city": "Dallas"
  },
  "usa-belgien": {
    "tempC": 11,
    "text": "bewölkt",
    "city": "Seattle"
  },
  "argentinien-agypten": {
    "tempC": 24,
    "text": "klar",
    "city": "Atlanta"
  },
  "schweiz-kolumbien": {
    "tempC": 11,
    "text": "klar",
    "city": "Vancouver"
  }
}
